README.md
setup.cfg
setup.py
totvserprmgam/__init__.py
totvserprmgam/auth.py
totvserprmgam/baseapi.py
totvserprmgam/educational.py
totvserprmgam/enabling.py
totvserprmgam/exceptions.py
totvserprmgam/financial.py
totvserprmgam/retrieve.py
totvserprmgam/utils.py
totvserprmgam.egg-info/PKG-INFO
totvserprmgam.egg-info/SOURCES.txt
totvserprmgam.egg-info/dependency_links.txt
totvserprmgam.egg-info/requires.txt
totvserprmgam.egg-info/top_level.txt