Metadata-Version: 1.0
Name: totvserprmgam
Version: 1.0.22
Summary: API para webservices do TOTVS ERP RM
Home-page: https://github.com/grupoandrademartins/totvserprm
Author: Rafael G. Winter, Túlio Cesar Martins
Author-email: totvs-erp-rm-python@googlegroups.com
License: MIT
Keywords: totvs webservice erp rm soap api
Platform: UNKNOWN
